mahjongpy/__init__.py
mahjongpy/mahjongplayer.py
mahjongpy/mahjongtable.py
mahjongpy/mahjongtile.py
mahjongpy-0.2.4.dist-info/LICENSE
mahjongpy-0.2.4.dist-info/METADATA
mahjongpy-0.2.4.dist-info/WHEEL
mahjongpy-0.2.4.dist-info/top_level.txt
mahjongpy-0.2.4.dist-info/RECORD
